stageflow/__init__.py
stageflow/py.typed
stageflow/testing.py
stageflow/builtins/__init__.py
stageflow/builtins/dicts.py
stageflow/builtins/lists.py
stageflow/builtins/lists_extra.py
stageflow/builtins/logic.py
stageflow/builtins/strings.py
stageflow/builtins/vars.py
stageflow/core/__init__.py
stageflow/core/context.py
stageflow/core/event.py
stageflow/core/jsonlogic.py
stageflow/core/node.py
stageflow/core/pipeline.py
stageflow/core/session.py
stageflow/core/stage.py
stageflow/core/utils.py
stageflow/docs/__init__.py
stageflow/docs/html.py
stageflow/docs/schema.py
stageflow/docs/schemas/pipeline.json
stageflow_framework-0.1.6.dist-info/METADATA
stageflow_framework-0.1.6.dist-info/WHEEL
stageflow_framework-0.1.6.dist-info/top_level.txt
stageflow_framework-0.1.6.dist-info/RECORD
