Metadata-Version: 2.4
Name: stageflow-framework
Version: 0.1.6
Summary: StageFlow: Pipeline framework for stages
Author: lethargy
Requires-Python: >=3.10
Requires-Dist: pyyaml
Requires-Dist: jsonschema>=4.0.0
